LICENSE
README.md
pyproject.toml
setup.cfg
setup.py
multicrypto/__init__.py
multicrypto/address.py
multicrypto/apis.py
multicrypto/base58.py
multicrypto/bech32.py
multicrypto/coins.py
multicrypto/consts.py
multicrypto/ecdsa.py
multicrypto/ellipticcurve.py
multicrypto/ethaddress.py
multicrypto/keccak.py
multicrypto/keccak2.py
multicrypto/log.py
multicrypto/network.py
multicrypto/numbertheory.py
multicrypto/ripemd160.py
multicrypto/scripts.py
multicrypto/transaction.py
multicrypto/utils.py
multicrypto/validators.py
multicrypto.egg-info/PKG-INFO
multicrypto.egg-info/SOURCES.txt
multicrypto.egg-info/dependency_links.txt
multicrypto.egg-info/entry_points.txt
multicrypto.egg-info/requires.txt
multicrypto.egg-info/top_level.txt
multicrypto/commands/__init__.py
multicrypto/commands/checkaddress.py
multicrypto/commands/genaddress.py
multicrypto/commands/sendcrypto.py
multicrypto/commands/signmessage.py
multicrypto/commands/sweepaddress.py
multicrypto/commands/transaddress.py
multicrypto/commands/transprivkey.py
multicrypto/commands/verifymessage.py