Metadata-Version: 2.1
Name: multicrypto
Version: 0.1.17
Summary: Tool for translating and creating custom addresses for various cryptocurrencies
Home-page: https://github.com/tompin/multicrypto
Author: tompin
Author-email: tompin@tuta.io
License: http://opensource.org/licenses/MIT
Keywords: cryptocurrency,address,transaction
Classifier: Development Status :: 3 - Alpha
Classifier: Intended Audience :: Developers
Classifier: Topic :: Security :: Cryptography
Classifier: Topic :: Software Development :: Libraries :: Python Modules
Classifier: License :: OSI Approved :: MIT License
Classifier: Programming Language :: Python :: 3
Classifier: Programming Language :: Python :: 3.8
Classifier: Programming Language :: Python :: 3.9
Classifier: Programming Language :: Python :: 3.10
Classifier: Programming Language :: Python :: 3.11
Classifier: Programming Language :: Python :: 3.12
License-File: LICENSE
